xrandr_manager/__init__.py
xrandr_manager/console.py
xrandr_manager/executor.py
xrandr_manager/manager.py
xrandr_manager/model.py
xrandr_manager/parser.py
xrandr_manager/prompt.py
xrandr_manager-0.1.0.dist-info/LICENSE
xrandr_manager-0.1.0.dist-info/METADATA
xrandr_manager-0.1.0.dist-info/WHEEL
xrandr_manager-0.1.0.dist-info/entry_points.txt
xrandr_manager-0.1.0.dist-info/top_level.txt
xrandr_manager-0.1.0.dist-info/RECORD
