Metadata-Version: 2.1
Name: xrandr-manager
Version: 0.1.0
Summary: Xrandr manager
Home-page: https://github.com/deresmos/xrandr-manager
Author: deresmos
Author-email: deresmos@gmail.com
License: MIT License
Keywords: tools
Platform: UNKNOWN
Requires-Python: >=3.7
Requires-Dist: prompt-toolkit
